uclasm/__init__.py
uclasm/counting/__init__.py
uclasm/counting/alldiffs.py
uclasm/counting/has_isomorphism.py
uclasm/counting/isomorphisms.py
uclasm/filters/__init__.py
uclasm/filters/elimination_filter.py
uclasm/filters/label_filter.py
uclasm/filters/neighborhood_filter.py
uclasm/filters/permutation_filter.py
uclasm/filters/run_filters.py
uclasm/filters/stats_filter.py
uclasm/filters/topology_filter.py
uclasm/filters/validation_filter.py
uclasm/utils/__init__.py
uclasm/utils/data_loaders.py
uclasm/utils/data_structures.py
uclasm/utils/graph_ops.py
uclasm/utils/misc.py
uclasm/utils/summarize.py
ucla_subgraph_matching-0.2.0.dist-info/LICENSE
ucla_subgraph_matching-0.2.0.dist-info/WHEEL
ucla_subgraph_matching-0.2.0.dist-info/METADATA
ucla_subgraph_matching-0.2.0.dist-info/RECORD
