Metadata-Version: 2.1
Name: ucla-subgraph-matching
Version: 0.2.0
Summary: 
Home-page: https://github.com/jdmoorman/uclasm
License: MIT
Author: Jacob Moorman
Author-email: jacob@moorman.me
Requires-Python: >=3.7,<4.0
Classifier: License :: OSI Approved :: MIT License
Classifier: Programming Language :: Python :: 3
Classifier: Programming Language :: Python :: 3.7
Classifier: Programming Language :: Python :: 3.8
Requires-Dist: networkx (>=2.4,<3.0)
Requires-Dist: numpy (>=1.18.1,<2.0.0)
Requires-Dist: pandas (>=1.0.1,<2.0.0)
Requires-Dist: scipy (>=1.4.1,<2.0.0)
Project-URL: Repository, https://github.com/jdmoorman/uclasm
